black_gl_code_quality/__init__.py
black_gl_code_quality/__main__.py
black_gl_code_quality/error.py
black_gl_code_quality/parser.py
black_gl_code_quality-0.3.1.dist-info/LICENSE
black_gl_code_quality-0.3.1.dist-info/METADATA
black_gl_code_quality-0.3.1.dist-info/WHEEL
black_gl_code_quality-0.3.1.dist-info/entry_points.txt
black_gl_code_quality-0.3.1.dist-info/RECORD
