Metadata-Version: 2.1
Name: black-gl-code-quality
Version: 0.3.1
Summary: A simple wrapper to convert Black outputs to codeclimate report format for GitLab-CI
Home-page: https://github.com/themimitoof/black-gl-code-quality
License: BSD-3-Clause
Keywords: Black,CodeClimate,GitLab,GitLab-CI,Code Quality
Author: Michael Vieira
Author-email: dev@mvieira.fr
Requires-Python: >=3.7,<4.0
Classifier: License :: OSI Approved :: BSD License
Classifier: Programming Language :: Python :: 3
Classifier: Programming Language :: Python :: 3.7
Classifier: Programming Language :: Python :: 3.8
Classifier: Programming Language :: Python :: 3.9
Classifier: Programming Language :: Python :: 3.10
Classifier: Programming Language :: Python :: 3.11
Classifier: Programming Language :: Python :: 3.12
Project-URL: Repository, https://github.com/themimitoof/black-gl-code-quality
